{"Rows":[{"Date":"2024-03-11~2024-03-17","Amount":67261.0000,"Tickets":320,"TotalAmount":146130.0000,"TotalTickets":689,"Rate":-0.1471807681091430092938924039,"TheaterCount":15},{"Date":"2024-03-18~2024-03-24","Amount":19130.0000,"Tickets":90,"TotalAmount":165260.0000,"TotalTickets":779,"Rate":-0.7155855547791439318475788347,"TheaterCount":9},{"Date":"2024-03-25~2024-03-31","Amount":740.0000,"Tickets":3,"TotalAmount":166000.0000,"TotalTickets":782,"Rate":-0.9613173026659696811291165708,"TheaterCount":1},{"Date":"2024-04-01~2024-04-07","Amount":null,"Tickets":null,"TotalAmount":166000.0000,"TotalTickets":782,"Rate":-1,"TheaterCount":0},{"Date":"2024-04-08~2024-04-14","Amount":null,"Tickets":null,"TotalAmount":166000.0000,"TotalTickets":782,"Rate":0,"TheaterCount":0},{"Date":"2024-04-15~2024-04-21","Amount":19440.0000,"Tickets":69,"TotalAmount":185440.0000,"TotalTickets":851,"Rate":0,"TheaterCount":1}]}